{
   "weeklychartlist":{
      "chart":[
         {
            "from":"1528027200",
            "to":"1528632000"
         },
         {
            "from":"1528632000",
            "to":"1529236800"
         },
         {
            "from":"1529236800",
            "to":"1529841600"
         },
         {
            "from":"1529841600",
            "to":"1530446400"
         },
         {
            "from":"1530446400",
            "to":"1531051200"
         },
         {
            "from":"1531051200",
            "to":"1531656000"
         },
         {
            "from":"1531656000",
            "to":"1532260800"
         },
         {
            "from":"1532260800",
            "to":"1532865600"
         },
         {
            "from":"1532865600",
            "to":"1533470400"
         },
         {
            "from":"1533470400",
            "to":"1534075200"
         },
         {
            "from":"1534075200",
            "to":"1534680000"
         },
         {
            "from":"1534680000",
            "to":"1535284800"
         },
         {
            "from":"1535284800",
            "to":"1535889600"
         },
         {
            "from":"1535889600",
            "to":"1536494400"
         },
         {
            "from":"1536494400",
            "to":"1537099200"
         },
         {
            "from":"1537099200",
            "to":"1537704000"
         },
         {
            "from":"1537704000",
            "to":"1538308800"
         },
         {
            "from":"1538308800",
            "to":"1538913600"
         },
         {
            "from":"1538913600",
            "to":"1539518400"
         },
         {
            "from":"1539518400",
            "to":"1540123200"
         },
         {
            "from":"1540123200",
            "to":"1540728000"
         },
         {
            "from":"1540728000",
            "to":"1541332800"
         },
         {
            "from":"1541332800",
            "to":"1541937600"
         },
         {
            "from":"1541937600",
            "to":"1542542400"
         }
      ]
   }
}